astro_platform_api_client/__init__.py
astro_platform_api_client/api/__init__.py
astro_platform_api_client/api/cluster/__init__.py
astro_platform_api_client/api/cluster/create_cluster.py
astro_platform_api_client/api/cluster/delete_cluster.py
astro_platform_api_client/api/cluster/get_cluster.py
astro_platform_api_client/api/cluster/list_clusters.py
astro_platform_api_client/api/cluster/update_cluster.py
astro_platform_api_client/api/deployment/__init__.py
astro_platform_api_client/api/deployment/create_deployment.py
astro_platform_api_client/api/deployment/delete_deployment.py
astro_platform_api_client/api/deployment/get_deployment.py
astro_platform_api_client/api/deployment/list_deployments.py
astro_platform_api_client/api/deployment/update_deployment.py
astro_platform_api_client/api/options/__init__.py
astro_platform_api_client/api/options/get_cluster_options.py
astro_platform_api_client/api/options/get_deployment_options.py
astro_platform_api_client/api/organization/__init__.py
astro_platform_api_client/api/organization/get_organization.py
astro_platform_api_client/api/organization/list_organizations.py
astro_platform_api_client/api/organization/update_organization.py
astro_platform_api_client/api/workspace/__init__.py
astro_platform_api_client/api/workspace/create_workspace.py
astro_platform_api_client/api/workspace/delete_workspace.py
astro_platform_api_client/api/workspace/get_workspace.py
astro_platform_api_client/api/workspace/list_workspaces.py
astro_platform_api_client/api/workspace/update_workspace.py
astro_platform_api_client/client.py
astro_platform_api_client/errors.py
astro_platform_api_client/models/__init__.py
astro_platform_api_client/models/basic_subject_profile.py
astro_platform_api_client/models/basic_subject_profile_subject_type.py
astro_platform_api_client/models/cluster.py
astro_platform_api_client/models/cluster_cloud_provider.py
astro_platform_api_client/models/cluster_k8s_tag.py
astro_platform_api_client/models/cluster_metadata.py
astro_platform_api_client-1b1.dist-info/METADATA
astro_platform_api_client-1b1.dist-info/WHEEL
astro_platform_api_client-1b1.dist-info/RECORD
